SegRunLib/__init__.py
SegRunLib/run.py
SegRunLib/ml/HessNet.py
SegRunLib/ml/controller.py
SegRunLib/ml/get_model.py
SegRunLib/ml/metrics.py
SegRunLib/ml/pytorch_ssim.py
SegRunLib/ml/soft_skeleton.py
SegRunLib/ml/tio_dataset.py
SegRunLib/ml/unet3d.py
SegRunLib/scripts/RunnerClass.py
SegRunLib/scripts/hessian_based.py
SegRunLib/scripts/nifty_utils.py
SegRunLib-0.0.6.dist-info/METADATA
SegRunLib-0.0.6.dist-info/WHEEL
SegRunLib-0.0.6.dist-info/top_level.txt
SegRunLib-0.0.6.dist-info/RECORD
