Metadata-Version: 2.1
Name: SegRunLib
Version: 0.0.6
Summary: This is the module for medical images segmentation
Home-page: https://github.com/NotYourLady
Author: msst
Author-email: mihailshutov105@gmail.com
Project-URL: GitHub, https://github.com/NotYourLady/SegRunLib
Keywords: ml nn cnn
Classifier: Programming Language :: Python :: 3.10
Classifier: Operating System :: OS Independent
Requires-Python: >=3.6
Requires-Dist: torch ==2.0.0
Requires-Dist: torchio ==0.19.2
Requires-Dist: nibabel ==5.1.0
Requires-Dist: tqdm ==4.66.1
